contextus/VERSION.txt
contextus/__init__.py
contextus-0.0.1.dist-info/LICENSE
contextus-0.0.1.dist-info/METADATA
contextus-0.0.1.dist-info/WHEEL
contextus-0.0.1.dist-info/top_level.txt
contextus-0.0.1.dist-info/RECORD
