Metadata-Version: 2.1
Name: contextus
Version: 0.0.1
Summary: contextus
Home-page: https://github.com/walkacross/contextus
Author: Jiang Yu
Author-email: yujiangallen@126.com
License: Apache License v2
Platform: UNKNOWN
Classifier: Programming Language :: Python
Classifier: Operating System :: Microsoft :: Windows
Classifier: Operating System :: Unix
Classifier: Programming Language :: Python :: 3.6
Classifier: Programming Language :: Python :: 3.7
